[{"id":"553184707414@s.whatsapp.net","saldo":1},{"id":"553190819299@s.whatsapp.net","saldo":1},{"id":"559391788143@s.whatsapp.net","saldo":1},{"id":"559186427691@s.whatsapp.net","saldo":1},{"id":"5512992480082@s.whatsapp.net","saldo":1},{"id":"556196697514@s.whatsapp.net","saldo":76},{"id":"554399118199@s.whatsapp.net","saldo":1},{"id":"79932411498@s.whatsapp.net","saldo":1},{"id":"554396385138@s.whatsapp.net","saldo":1},{"id":"559391912460@s.whatsapp.net","saldo":1},{"id":"555181686091@s.whatsapp.net","saldo":1},{"id":"5512996378494@s.whatsapp.net","saldo":1},{"id":"558597596278@s.whatsapp.net","saldo":1},{"id":"553197309370@s.whatsapp.net","saldo":1},{"id":"5521982883384@s.whatsapp.net","saldo":1},{"id":"558781125505@s.whatsapp.net","saldo":1},{"id":"258833741879@s.whatsapp.net","saldo":1},{"id":"258858119033@s.whatsapp.net","saldo":1}]